SimuConvert/__init__.py
SimuConvert/zuhedashi_convert.py
SimuConvert-0.0.3.dist-info/LICENSE
SimuConvert-0.0.3.dist-info/METADATA
SimuConvert-0.0.3.dist-info/WHEEL
SimuConvert-0.0.3.dist-info/top_level.txt
SimuConvert-0.0.3.dist-info/RECORD
