Metadata-Version: 2.1
Name: SimuConvert
Version: 0.0.3
Summary: A package for converting private fund equity data 
Home-page: https://github.com/Yanzhong-Hub/SimuConvert
Author: Yanzhong Huang
Author-email: yanzhong.huang@outlook.com
License: MIT
Classifier: Programming Language :: Python :: 3
Classifier: License :: OSI Approved :: MIT License
Requires-Python: >=3.6
License-File: LICENSE
Requires-Dist: pandas (>=1.5.0)
Requires-Dist: openpyxl (>=3.0.0)
Provides-Extra: dev
Requires-Dist: pytest (>=7.0) ; extra == 'dev'
Requires-Dist: twine (>=4.0.2) ; extra == 'dev'
